SpAlgo/__init__.py
SpAlgo/_closest_pair/__init__.py
SpAlgo/_closest_pair/_closest.py
SpAlgo/_closest_pair/_point.py
SpAlgo/_knapsack/__init__.py
SpAlgo/_knapsack/_knapsack.py
SpAlgo/_knapsack/_pack.py
SpAlgo/_knapsack/_qsort.py
SpAlgo/_peak/__init__.py
SpAlgo/_peak/_array.py
SpAlgo/_peak/_matrix.py
SpAlgo/_sequences/__init__.py
SpAlgo/_sequences/_sequence.py
SpAlgo/numerical_analysis/__init__.py
SpAlgo/numerical_analysis/bin_to_float.py
SpAlgo/numerical_analysis/newton_method.py
SpAlgo/numerical_analysis/secant_method.py
SpAlgo-0.4.0.dist-info/LICENSE
SpAlgo-0.4.0.dist-info/METADATA
SpAlgo-0.4.0.dist-info/WHEEL
SpAlgo-0.4.0.dist-info/top_level.txt
SpAlgo-0.4.0.dist-info/RECORD
